{
   "Changes": [
      {
         "Action": "EditData",
         "Target": "Characters/Dialogue/Arvey",
         "Entries": {
            "Introduction": "{{i18n:Dialogue.Arvey.Introduction}}",
            "spring_1_2": "{{i18n:Dialogue.Arvey.spring_1_2}}",
            "GreenRain": "{{i18n:Dialogue.Arvey.GreenRain}}",
            "MovieInvitation": "{{i18n:Dialogue.Arvey.MovieInvitation}}",
            "AcceptBirthdayGift_Loved": "{{i18n:Dialogue.Arvey.AcceptBirthdayGift_Loved}}",
            "AcceptBirthdayGift_Liked": "{{i18n:Dialogue.Arvey.AcceptBirthdayGift_Liked}}",
            "AcceptBirthdayGift_Neutral": "{{i18n:Dialogue.Arvey.AcceptBirthdayGift_Neutral}}",
            "AcceptBirthdayGift_Disliked": "{{i18n:Dialogue.Arvey.AcceptBirthdayGift_Disliked}}",
            "AcceptBirthdayGift_Hated": "{{i18n:Dialogue.Arvey.AcceptBirthdayGift_Hated}}",
            "AcceptGift_(O)StardropTea": "{{i18n:Dialogue.Arvey.AcceptGift_(O)StardropTea}}",
            "Resort": "{{i18n:Dialogue.Arvey.Resort}}",
            "Resort_Bar": "{{i18n:Dialogue.Arvey.Resort_Bar}}",
            "Resort_Chair": "{{i18n:Dialogue.Arvey.Resort_Chair}}",
            "Resort_Dance": "{{i18n:Dialogue.Arvey.Resort_Dance}}",
            "Resort_Entering": "{{i18n:Dialogue.Arvey.Resort_Entering}}",
            "Resort_Leaving": "{{i18n:Dialogue.Arvey.Resort_Leaving}}",
            "Resort_Shore": "{{i18n:Dialogue.Arvey.Resort_Shore}}",
            "Resort_Towel": "{{i18n:Dialogue.Arvey.Resort_Towel}}",
            "Resort_Umbrella": "{{i18n:Dialogue.Arvey.Resort_Umbrella}}",
            "Resort_Wander": "{{i18n:Dialogue.Arvey.Resort_Wander}}",
            "Mon": "{{i18n:Dialogue.Arvey.Mon}}",
            "Mon2": "{{i18n:Dialogue.Arvey.Mon2}}",
            "Mon4": "{{i18n:Dialogue.Arvey.Mon4}}",
            "Mon6": "{{i18n:Dialogue.Arvey.Mon6}}",
            "Mon8": "{{i18n:Dialogue.Arvey.Mon8}}",
            "Mon10": "{{i18n:Dialogue.Arvey.Mon10}}",
            "Tue": "{{i18n:Dialogue.Arvey.Tue}}",
            "Tue2": "{{i18n:Dialogue.Arvey.Tue2}}",
            "Tue4": "{{i18n:Dialogue.Arvey.Tue4}}",
            "Tue6": "{{i18n:Dialogue.Arvey.Tue6}}",
            "Tue8": "{{i18n:Dialogue.Arvey.Tue8}}",
            "Tue10": "{{i18n:Dialogue.Arvey.Tue10}}",
            "Wed": "{{i18n:Dialogue.Arvey.Wed}}",
            "Wed2": "{{i18n:Dialogue.Arvey.Wed2}}",
            "Wed4": "{{i18n:Dialogue.Arvey.Wed4}}",
            "Wed6": "{{i18n:Dialogue.Arvey.Wed6}}",
            "Wed8": "{{i18n:Dialogue.Arvey.Wed8}}",
            "Wed10": "{{i18n:Dialogue.Arvey.Wed10}}",
            "Thu": "{{i18n:Dialogue.Arvey.Thu}}",
            "Thu2": "{{i18n:Dialogue.Arvey.Thu2}}",
            "Thu4": "{{i18n:Dialogue.Arvey.Thu4}}",
            "Thu6": "{{i18n:Dialogue.Arvey.Thu6}}",
            "Thu8": "{{i18n:Dialogue.Arvey.Thu8}}",
            "Thu10": "{{i18n:Dialogue.Arvey.Thu10}}",
            "Fri": "{{i18n:Dialogue.Arvey.Fri}}",
            "Fri2": "{{i18n:Dialogue.Arvey.Fri2}}",
            "Fri4": "{{i18n:Dialogue.Arvey.Fri4}}",
            "Fri6": "{{i18n:Dialogue.Arvey.Fri6}}",
            "Fri8": "{{i18n:Dialogue.Arvey.Fri8}}",
            "Fri10": "{{i18n:Dialogue.Arvey.Fri10}}",
            "Sat": "{{i18n:Dialogue.Arvey.Sat}}",
            "Sat2": "{{i18n:Dialogue.Arvey.Sat2}}",
            "Sat4": "{{i18n:Dialogue.Arvey.Sat4}}",
            "Sat6": "{{i18n:Dialogue.Arvey.Sat6}}",
            "Sat8": "{{i18n:Dialogue.Arvey.Sat8}}",
            "Sat10": "{{i18n:Dialogue.Arvey.Sat10}}",
            "Sun": "{{i18n:Dialogue.Arvey.Sun}}",
            "Sun2": "{{i18n:Dialogue.Arvey.Sun2}}",
            "Sun4": "{{i18n:Dialogue.Arvey.Sun4}}",
            "Sun6": "{{i18n:Dialogue.Arvey.Sun6}}",
            "Sun8": "{{i18n:Dialogue.Arvey.Sun8}}",
            "Sun10": "{{i18n:Dialogue.Arvey.Sun10}}"
         }
      }
   ]
}