{
    /* [Dialogue] Arkwright */
    /*+++++++++++++++++++++++++++++++++++++++++++++++++++++++++++++++++++++++++++++++++++++++++++++++++++++++++++*/
    //[Arkwright Dialogue] Special
    "SDS.Dialogue.Arkwright.Introduction": "我是阿克赖特……呃，如你所见，是卖肉的。$0",
    /*~*~*~*/
    "SDS.Dialogue.Arkwright.spring_1_2": "你好，新年快乐。$1#$e#本来我不应该在新年出来工作的，但是家里只有我一个人有点冷清，所以我还是到店里来了。$0#$b#至少这里要比我家热闹的多。$1",
    "SDS.Dialogue.Arkwright.spring_12": "你也要去找彩蛋？在草丛里走来走去还是挺有意思的，第一名会有什么奖励吗？$0",
    "SDS.Dialogue.Arkwright.spring_23": "大家聚在一起跳舞听起来挺有意思的，会让我想起以前军队里的文艺汇演，不过我什么才艺都没有，只负责在台下鼓掌。$0#$b#祝你玩得开心。$1",
    "SDS.Dialogue.Arkwright.summer_10": "你可以在汤里放切成小块的肉，这样总不会出错的，而且尝起来很鲜。有人在汤里放奇怪的东西另说。$0",
    "SDS.Dialogue.Arkwright.summer_27": "月光水母听起来就很漂亮，那样的场景一定会令人难忘吧。$1",
    "SDS.Dialogue.Arkwright.fall_15": "你一定为这次展览准备了很久吧，希望你能得到个好名次。$1",
    "SDS.Dialogue.Arkwright.fall_26": "所以你明天也会去那个迷宫吗？$0",
    "SDS.Dialogue.Arkwright.winter_7": "这种寒冷的天气也要在外面举行节日吗。$0",
    "SDS.Dialogue.Arkwright.winter_24": "大家互相交换礼物的节日听起来还不错，要不然我也买点什么寄给我的老战友？$0",
    "SDS.Dialogue.Arkwright.GreenRain": "还是尽量待在室内吧，毕竟没办法确定这雨对人体有什么危害。$0",
    "SDS.Dialogue.Arkwright.AcceptGift_(O)StardropTea": "给、给我的？呃…我是说我很喜欢！谢谢你，真的。$1",
    "SDS.Dialogue.Arkwright.MovieInvitation": "那里会有小孩吗，我需不需要带个口罩。$1",
    /*+++++++++++++++++++++++++++++++++++++++++++++++++++++++++++++++++++++++++++++++++++++++++++++++++++++++++++*/
    //[Arkwright Dialogue] Resort
    "SDS.Dialogue.Arkwright.Resort": "……你好，今天的天气真不错。$1",
    "SDS.Dialogue.Arkwright.Resort_Bar": "有什么想买的吗？这边的一款特调酒味道很好，我给安妮卡女士也推荐过，她喝完以后赞不绝口。$1",
    "SDS.Dialogue.Arkwright.Resort_Chair": "%阿克赖特似乎在发呆，不知道在想什么",
    "SDS.Dialogue.Arkwright.Resort_Dance": "要来跳一支舞吗？安妮卡女士之前问我要不要谈恋爱的时候教过我跳舞，当时我的动作太笨拙，差点踩到了她的鞋子……$1",
    "SDS.Dialogue.Arkwright.Resort_Entering": "嗯……姜岛的景色很漂亮。$1",
    "SDS.Dialogue.Arkwright.Resort_Leaving": "再见，@，我该回去了。$0",
    "SDS.Dialogue.Arkwright.Resort_Shore": "%阿克赖特没有说话，只是轻轻闭上眼睛享受从海面吹来带有咸湿气息的风。阿克赖特没有说话，只是轻轻闭上眼睛享受从海面吹来带有咸湿气息的风。",
    "SDS.Dialogue.Arkwright.Resort_Towel": "要来这里歇会吗？看你已经满头大汗了。$0",
    "SDS.Dialogue.Arkwright.Resort_Umbrella": "佩莱特真的要把自己的皮肤晒成古铜色吗……$2#$b#你认为哪种肤色对于他来说更好看？毕竟你更了解他一点。$0",
    "SDS.Dialogue.Arkwright.Resort_Wander": "要一起在沙滩上走走吗？$0",
    /*+++++++++++++++++++++++++++++++++++++++++++++++++++++++++++++++++++++++++++++++++++++++++++++++++++++++++++*/
    //[Arkwright Dialogue] General/Spring
    "SDS.Dialogue.Arkwright.spring_Mon": "需要什么？随便看看。$0#$b#%阿克赖特站在柜台后面大声喊着，他好像没注意到自己说话很大声。",
    "SDS.Dialogue.Arkwright.spring_Mon2": "%阿克赖特看见你后对你微微点了点头。",
    "SDS.Dialogue.Arkwright.spring_Mon4": "你也认识安妮卡女士吗？她对我很好，总是会带甜品过来和我聊上一会儿，所以我通常都给她打很多折扣。$1",
    "SDS.Dialogue.Arkwright.spring_Mon6": "你们镇上是不是有个叫佩莱特的人？他有时候会卖给我一些新鲜的肉，他说都是靠打猎抓到的，真厉害啊。$1",
    "SDS.Dialogue.Arkwright.spring_Mon8": "安妮卡女士之前给了我好几条围巾，她说是给我和我的狗狗们的，等到了天冷的时候就能用上了。真不知道该怎么感谢她。$1",
    "SDS.Dialogue.Arkwright.spring_Mon10": "你和安妮卡女士都很好，很热心，大概是我在这座城市里为数不多的朋友了，认识你们我很高兴。$1#$b#唉，真没想到当初那么多的战友现在都各奔东西了...$0",
    "SDS.Dialogue.Arkwright.spring_Tue": "需要什么自己选。$0",
    "SDS.Dialogue.Arkwright.spring_Tue2": "我店里卖的肉都很新鲜，放心。$1%阿克赖特的声音隆隆响起。",
    "SDS.Dialogue.Arkwright.spring_Tue4": "你、你好，是来买肉的吗？$0#$b#唉...我这不是废话吗...别介意，我只是想试着友善地打招呼。$2",
    "SDS.Dialogue.Arkwright.spring_Tue6": "我以前试着在镜子前练习微笑发现看起来反而更凶了，最后还是戴上口罩比较好啊。而且戴口罩我的嗓门也听起来不那么大，应该不会再吓到别人了。$5",
    "SDS.Dialogue.Arkwright.spring_Tue8": "如果安妮卡女士在你面前说了关于我的一些事，你别在意。我觉得她对我的评价有点过头了，我没那么好。$0",
    "SDS.Dialogue.Arkwright.spring_Tue10": "你应该也看出来了，我不怎么会聊天，安妮卡女士说我得主动些才有机会，说实话我没听懂...她当时还冲着我神秘地眨了眨眼。$0",
    "SDS.Dialogue.Arkwright.spring_Wed": "你要买什么？$0",
    "SDS.Dialogue.Arkwright.spring_Wed2": "来点什么？$0#$b#%阿克赖特似乎没意识到他手里的刀很有威慑力...",
    "SDS.Dialogue.Arkwright.spring_Wed4": "你说我脸上的疤？那是我在抓流浪猫去绝育的时候不小心被挠开的，我知道它不是故意的，它只是太害怕了。$2",
    "SDS.Dialogue.Arkwright.spring_Wed6": "安妮卡女士和我提到过你，她对你的评价不错，真的...我也很认同她的话。$1",
    "SDS.Dialogue.Arkwright.spring_Wed8": "自从安妮卡女士知道我喜欢甜食之后，她时不时就会送来一些。$0#$b#虽然很感谢她，但是送来的数量有点多了...要是拒绝她的话会让她难过吧。唉...$2",
    "SDS.Dialogue.Arkwright.spring_Wed10": "我休息的时候会找个热闹的街边坐着，看着人来人往，大家都忙于自己的事情，然后我就会想这样和平的日子也很不错。$1#$b#就是过去总是和战友们睡在一个宿舍里，现在只有我一个人住还是很难习惯...$0",
    "SDS.Dialogue.Arkwright.spring_Thu": "%阿克赖特盯着你不说话...啊，他把视线移开了。",
    "SDS.Dialogue.Arkwright.spring_Thu2": "嗯...你好。$0",
    "SDS.Dialogue.Arkwright.spring_Thu4": "你别误会啊，我不是什么黑店老板，也不是什么混混...你笑什么？难不成我说错话了？$0",
    "SDS.Dialogue.Arkwright.spring_Thu6": "要说关系不错的人，佩莱特也算是一个，毕竟他时不时会来我这一趟，一来二去就熟悉了。$0",
    "SDS.Dialogue.Arkwright.spring_Thu8": "你会不会觉得我喜欢吃甜的很奇怪...？我没有别的意思，只是从表面来看，我这样的人和甜品很不搭啊。$0#$b#大概是因为在军队的时候很少吃到蛋糕之类的吧，所以现在总是会忍不住想吃。$1",
    "SDS.Dialogue.Arkwright.spring_Thu10": "嗯？哦抱歉，我只是在统计最近几天的营业额。你不介意的话在旁边等一会吧，我给你拿点饼干。$1#$b#其实我还有一些退伍补助金，不过那大部分都用来给附近的流浪动物绝育了，要抓住那些警觉的小动物可不是件容易的事。$1",
    "SDS.Dialogue.Arkwright.spring_Fri": "买点什么？$0",
    "SDS.Dialogue.Arkwright.spring_Fri2": "你好…要点什么？$0#$b#%阿克赖特看着你。",
    "SDS.Dialogue.Arkwright.spring_Fri4": "曾经有人刚踏进店门就因为看到我的长相而扭头离开，所以你第一次来的时候我在想你会不会也那样...$2#$b#啊，对不起，我是不是不该这样说，我没那个意思的。$2",
    "SDS.Dialogue.Arkwright.spring_Fri6": "安妮卡女士人很好，只不过有些时候实在是...你懂吗？我有点招架不住。$2",
    "SDS.Dialogue.Arkwright.spring_Fri8": "你好啊，我正在读战友给我寄来的信，我们虽然都回到了各自的家乡，但还是保持联系，偶尔也会聚一聚。他们还给送给我很多特产，要不要尝尝看？$1",
    "SDS.Dialogue.Arkwright.spring_Fri10": "你在农场里也有领养宠物吗？照顾它们实在是件麻烦事，你得包容他们的一切，不过看到它们能快乐的生活，就又觉得所有幸苦都是值得的了。$1",
    "SDS.Dialogue.Arkwright.spring_Sat": "买什么？$0",
    "SDS.Dialogue.Arkwright.spring_Sat2": "你好。$0#$b#%阿克赖特陷入了沉默。",
    "SDS.Dialogue.Arkwright.spring_Sat4": "我总是控制不了大声说话，请别介意，那都是在没退役前留下的习惯了。$2",
    "SDS.Dialogue.Arkwright.spring_Sat6": "安妮卡女士之前有问我要不要谈个恋爱之类的，其实我单身这么多年倒也习惯了，也没想过会有人喜欢我，现在这样就挺好的。$1#$b#请你别告诉安妮卡女士，我知道她是好心。$0",
    "SDS.Dialogue.Arkwright.spring_Sat8": "我年轻的时候就这样了，明明想摆出友善的表情，结果总是把人吓跑。$1#$b#你说我现在这样就很好...？呃，是、是这样吗？$0",
    "SDS.Dialogue.Arkwright.spring_Sat10": "我很感谢你，虽然我已经习惯了大家对我疏远的态度，但是真正能有愿意和自己聊天的朋友感觉很好。$1",
    "SDS.Dialogue.Arkwright.spring_Sun": "你要买什么？随便看看吧。$0",
    "SDS.Dialogue.Arkwright.spring_Sun2": "你这次需要买多少？$0",
    "SDS.Dialogue.Arkwright.spring_Sun4": "我也不想吓到别人，但不管我做什么表情都看起来很凶，大家会害怕我也是正常的，但长什么也不是我能控制的啊，唉…抱歉，我不应该向你倒苦水的。$2",
    "SDS.Dialogue.Arkwright.spring_Sun6": "我偶尔会带我的狗狗们去草地上玩飞盘，它们很会讨小孩子喜欢，大概只有和它们呆在一起的时候，我才显得没有那么可怕吧。$0",
    "SDS.Dialogue.Arkwright.spring_Sun8": "佩莱特和我提到过你，明明是农场主，涉及的东西却特别多啊...啊，我的意思是你很厉害。$1",
    "SDS.Dialogue.Arkwright.spring_Sun10": "谢谢你能理解我，有时候我真的很担心自己说的话会不会有什么问题让别人误会。能认识你和安妮卡女士，我很高兴。$1",
    /*+++++++++++++++++++++++++++++++++++++++++++++++++++++++++++++++++++++++++++++++++++++++++++++++++++++++++++*/
    //[Arkwright Dialogue] Summer
    "SDS.Dialogue.Arkwright.summer_Mon": "新鲜的好肉，看看吧。$0",
    "SDS.Dialogue.Arkwright.summer_Mon2": "你好，来点什么？$0#$b#%阿克赖特看了你一眼便接着切肉了。",
    "SDS.Dialogue.Arkwright.summer_Mon4": "柜台旁的甜品？那是安妮卡女士送来的，她人很好。$1#$b#——你要来点吗？我吃不完。$0",
    "SDS.Dialogue.Arkwright.summer_Mon6": "谢谢你啊，没有在第一次进来看到我的时候转身跑开。$0#$b#%阿克赖特挤出了一抹看起来有点狰狞的微笑。",
    "SDS.Dialogue.Arkwright.summer_Mon8": "佩莱特偶尔过来，我们是在军营里认识的，闲的时候我们就一起做些菜放在店里卖。$1#$b#但客人们在门口望一眼就跑了，唉。$2",
    "SDS.Dialogue.Arkwright.summer_Mon10": "天气太热了，就算有冷柜肉也不会放到第二天，我绝对不会卖不新鲜的肉。$0#$b#剩下的肉怎么办？下班后我会带去给救助站的动物们吃，看着它们狼吞虎咽的样子很安心。$1",
    "SDS.Dialogue.Arkwright.summer_Tue": "来点什么？$0",
    "SDS.Dialogue.Arkwright.summer_Tue2": "刚切的肉，很新鲜。$0#$b#%阿克赖特拿着刀介绍着，鲜红的血沿着刀尖滴到了桌案上，真的是很新鲜的肉呢。",
    "SDS.Dialogue.Arkwright.summer_Tue4": "别看我长这样，我在救助站里获得过最受小动物欢迎奖。你别笑啊，真的！$0",
    "SDS.Dialogue.Arkwright.summer_Tue6": "你好，欢迎来买肉——$1#$b#我在练习友善的和客人打招呼，看起来怎么样？$0#$b#%虽然还是有些狰狞，但比上次好多了。",
    "SDS.Dialogue.Arkwright.summer_Tue8": "为什么要卖佩莱特做的饭？$0#$b#奥，我觉得他做出来的饭很不一样。做饭的时候放的调料和食材从来没有在别的地方见过，可以作为一个特色菜来卖。$1",
    "SDS.Dialogue.Arkwright.summer_Tue10": "你来了？$1#$b#我做了些家常菜，正准备叫你和安妮卡女士一起来吃呢，要喝茶吗？$0#$b#%阿克赖特为你拉开椅子示意你坐下，还贴心地弹了弹灰。",
    "SDS.Dialogue.Arkwright.summer_Wed": "……#$b#%阿克赖特盯着门口发呆，见你突然进来后他立刻转身切肉去了。",
    "SDS.Dialogue.Arkwright.summer_Wed2": "想买什么？我这的肉都不错。$1#$b#%阿克赖特没有注意到血溅到了他的围裙上。",
    "SDS.Dialogue.Arkwright.summer_Wed4": "呃……你想不想养一只……算了没什么，抱歉。$0#$b#%阿克赖特欲言又止，他懊恼地挠了挠头不再看你。",
    "SDS.Dialogue.Arkwright.summer_Wed6": "@，上次我其实想问你想不想领养救助站的动物，但我有些说不出口。$2#$b#现在我们成为朋友了，如果你愿意的话可以去玛妮的店里领养，记得领养前提前为小动物准备好碗。$1",
    "SDS.Dialogue.Arkwright.summer_Wed8": "戴着口罩是因为身体不舒服吗？$0#$b#谢谢你的关心，我没有生病，只是在想是不是把这张脸遮住就不会吓跑客人了。果然还是因为这张脸生意才不太好的吧，唉。$2",
    "SDS.Dialogue.Arkwright.summer_Wed10": "周末的时候我会带着狗狗们在公园里跑步，它们很喜欢比谁跑得快。$1我总是要费很大的力气才能控制住它们不撞到别人，后来我就渐渐只在清晨和深夜带它们玩了。$0",
    "SDS.Dialogue.Arkwright.summer_Thu": "随便看看。$0",
    "SDS.Dialogue.Arkwright.summer_Thu2": "你好。$0#$b#%阿克赖特低沉又沙哑的嗓音传来，像一个砂轮重重敲在了你的耳膜上。",
    "SDS.Dialogue.Arkwright.summer_Thu4": "如果你有多的鱼可以卖给我，我会把它们做成烤鱼。$1",
    "SDS.Dialogue.Arkwright.summer_Thu6": "你认识佩莱特吗？上次我们一起做饭时提起了你。$1#$b#我们都认为你是一个很厉害的人，年纪轻轻独自经营农场，不但什么都懂而且对谁都很友好。$0",
    "SDS.Dialogue.Arkwright.summer_Thu8": "天气很热，想来点烤肉吗？$1#$b#——哈啊，我在说什么啊，我只是想试试和客人随意聊两句。但是把大热天和烤肉放在一起好像不太合适。$2",
    "SDS.Dialogue.Arkwright.summer_Thu10": "没想到除了安妮卡女士外还有人愿意和我交谈，谢谢你愿意和我成为朋友，我很高兴。$1#$b#下班后要不要一起去救助站看看小动物？它们一定会很喜欢你的。$0",
    "SDS.Dialogue.Arkwright.summer_Fri": "要什么？$0",
    "SDS.Dialogue.Arkwright.summer_Fri2": "你好。$0#$b#%阿克赖特对你微微点头后马上移开了视线。",
    "SDS.Dialogue.Arkwright.summer_Fri4": "我曾听到有人叫我刀哥，这是为什么呢？$0#$b#你说是因为脸上的疤？可是这不是刀疤啊，只是小猫抓的而已，小猫也不是故意的，唉。$2",
    "SDS.Dialogue.Arkwright.summer_Fri6": "安妮卡女士今天去了邮局，顺便帮我带回了战友们写给我的信。$0#$b#虽然战争结束后我们去了不同的城市，但一直都在联系。$1",
    "SDS.Dialogue.Arkwright.summer_Fri8": "其实我不懂为什么要在夏天做百乐汤，这么热的天气，新鲜的肉和其他食材都要坏了，多浪费啊！$0#$b#%阿克赖特有些激动，本就洪亮的声音更大了。",
    "SDS.Dialogue.Arkwright.summer_Fri10": "大家对你的评价都很好，真羡慕你啊，怎样才能不吓到别人呢？$2#$b#——我现在这样就很好？$0#$b#你别开玩笑了——$2#$b#你是真诚建议的？好吧，我会保持的，谢谢你。$1",
    "SDS.Dialogue.Arkwright.summer_Sat": "买肉吗？",
    "SDS.Dialogue.Arkwright.summer_Sat2": "呃，你好，这里有烤肉……$0#$b#%阿克赖特的声音越来越小，最后放弃了介绍。",
    "SDS.Dialogue.Arkwright.summer_Sat4": "好热啊，要来点冰激凌吗？冰柜里有刚从超市买回来的。$1",
    "SDS.Dialogue.Arkwright.summer_Sat6": "佩莱特战斗能力非常强，他能徒手打死两只老虎，他家里的动物皮装饰都是他自己猎的，然后把肉送给了我，真厉害啊。$1",
    "SDS.Dialogue.Arkwright.summer_Sat8": "我和安妮卡女士是怎么认识的？$0#$b#呃，其实是有一次我将限量发行的巧克力蛋糕让给了安妮卡女士，自那以后安妮卡女士就经常过来坐坐。$1",
    "SDS.Dialogue.Arkwright.summer_Sat10": "开着一间肉铺还交到了能说话的朋友，这样平和的日子曾经做梦都不敢想。$1#$b#我经常写信告诉战友们我的生活，@要来亲自写讲你的那部分吗？$0",
    "SDS.Dialogue.Arkwright.summer_Sun": "要新鲜的肉吗？",
    "SDS.Dialogue.Arkwright.summer_Sun2": "……$0#$b#%阿克赖特看着你没有说话，他好像在对你点头。",
    "SDS.Dialogue.Arkwright.summer_Sun4": "为什么喜欢甜品？因为吃甜的心情会变好，你也可以试试。$1",
    "SDS.Dialogue.Arkwright.summer_Sun6": "今天真的很热，你的脸很红，喝点冰绿茶解解暑吧，要注意自己的身体啊。$0#$b#%阿克赖特拍了拍你的肩，力气有点大拍的你一个趔趄。",
    "SDS.Dialogue.Arkwright.summer_Sun8": "救助动物的原因？$0#$b#这没什么特别的，只是看着流浪的小动物们想到了战争结束没地方去的我。$2#$b#这座城市接受了我，我希望也能帮助这座城市其他没有家的动物。$1",
    "SDS.Dialogue.Arkwright.summer_Sun10": "安妮卡女士是个热心肠，她偶尔会问我要不要谈个恋爱，说我肯定会受到姑娘们的喜欢。$0#$b#但是我这个样子还没开口就能把客人吓跑也就你和安妮卡女士会觉得我是个好人了。$2#$b#和我交谈后就知道我人很好？$0#$b#%苦笑",
    /*+++++++++++++++++++++++++++++++++++++++++++++++++++++++++++++++++++++++++++++++++++++++++++++++++++++++++++*/
    //[Arkwright Dialogue] Fall
    "SDS.Dialogue.Arkwright.fall_Mon": "你好。$0#$b#%阿克赖特认真地看着你。",
    "SDS.Dialogue.Arkwright.fall_Mon2": "随意看看吧。",
    "SDS.Dialogue.Arkwright.fall_Mon4": "今天卖点什么？不好意思，买点什么才对。$0#$b#%阿克赖特看起来很尴尬，他的耳朵尖有些红。",
    "SDS.Dialogue.Arkwright.fall_Mon6": "狗狗们很喜欢秋天，它们喜欢钻到厚厚的落叶下面玩捉迷藏。$1#$b#虽然玩的很开心但这增加了我给它们洗澡的难度。$0#$b#%虽然阿克赖特语气烦恼，但他的脸上露出了柔和的表情。",
    "SDS.Dialogue.Arkwright.fall_Mon8": "我没有真正上过战场，我在军营接受训练还没到期时战争就结束了。$0#$b#为没能上战场感到遗憾吗？不会，没有人比军人更希望和平。$1",
    "SDS.Dialogue.Arkwright.fall_Mon10": "我和安妮卡女士认识很多年了，她是一位很出名的珠宝设计师。$1#$b#她说如果我有喜欢的姑娘一定要告诉她，她亲自为我设计求婚的珠宝，我只能硬着头皮谢谢她的好意然后生硬地转移话题。$0",
    "SDS.Dialogue.Arkwright.fall_Tue": "……$0#$b#%阿克赖特飞快瞄了你一眼没有说话。",
    "SDS.Dialogue.Arkwright.fall_Tue2": "你好，那个……来点什么？",
    "SDS.Dialogue.Arkwright.fall_Tue4": "不好意思今天开门有些晚了，方便的话能麻烦你看一下柜台上的传单吗……$0#$b#%阿克赖特的声音越来越小，你差点没听清最后几个字。",
    "SDS.Dialogue.Arkwright.fall_Tue6": "隔壁甜品店的店主是一个小姑娘，为了不吓到她我总是戴着帽子和口罩去买甜品，她总是笑眯眯地为我打包，看来这幅装扮很合适。$1",
    "SDS.Dialogue.Arkwright.fall_Tue8": "为什么以前有时看到你却不说话？$0#$b#我为以前没礼貌的行为道歉，我只是不好意思向你打招呼而已。请别介意，现在我已经能很流畅地跟你聊天了。$1",
    "SDS.Dialogue.Arkwright.fall_Tue10": "在军营的时候我最喜欢的就是秋天，没有夏天那么多的蚊虫也没有冬天那么寒冷，也不用担心饿一顿饱一顿，因为到处都可以找到不错的食物。$1",
    "SDS.Dialogue.Arkwright.fall_Wed": "随便看。",
    "SDS.Dialogue.Arkwright.fall_Wed2": "要买肉吗？$4#$b#%阿克赖特戴着帽子和口罩，他眼睛有点弯弯的好像在笑。",
    "SDS.Dialogue.Arkwright.fall_Wed4": "安妮卡女士经常叫我一起喝绿茶，还会教我泡绿茶的技巧，我很感谢她。$1",
    "SDS.Dialogue.Arkwright.fall_Wed6": "昨天散步的时候我好像在海里看到了美人鱼，蓝色的长头发和闪着光的鱼尾巴，真是美丽的让人不敢相信自己的眼睛。$0",
    "SDS.Dialogue.Arkwright.fall_Wed8": "佩莱特很容易生气，这只是多年在战场上紧绷神经留下来的后遗症。$0#$b#如果他对你发了脾气，我代他向你道歉，他人真的很不错。$2",
    "SDS.Dialogue.Arkwright.fall_Wed10": "秋天正是丰收的季节，有很多美味的食材只有在这个季节才会成熟。$1#$b#如果你的农场有什么少见的作物，可以卖给我一些吗？$0#$b#作为回报我会为你准备一顿丰盛大餐的。$1",
    "SDS.Dialogue.Arkwright.fall_Thu": "要多少？$4#$b#%阿克赖特整理了一下围裙，拿起刀准备切肉。",
    "SDS.Dialogue.Arkwright.fall_Thu2": "你好，随便看看。",
    "SDS.Dialogue.Arkwright.fall_Thu4": "今天天气不错，很适合散步。$0#$b#%阿克赖特在努力和你寒暄。",
    "SDS.Dialogue.Arkwright.fall_Thu6": "长着这么凶的脸是不是和甜品很不搭？所以我总是趁着没人的时候才吃。$0#$b#%你看到阿克赖特的脸红了。",
    "SDS.Dialogue.Arkwright.fall_Thu8": "这个季节森林里到处都是蘑菇，蘑菇的味道很鲜美，但是要小心识别哪些有毒哪些没毒，千万不可以为了追求刺激故意去吃毒蘑菇啊！$0",
    "SDS.Dialogue.Arkwright.fall_Thu10": "你看这块带筋的肉，如果想要喂给体型较小的狗一定要切的小一些，防止它们卡住气管——$0#$b#抱歉我没有说教的意思——$2#$b#很有用的小知识？没有让你感到不舒服就好。$1",
    "SDS.Dialogue.Arkwright.fall_Fri": "来点什么？$4",
    "SDS.Dialogue.Arkwright.fall_Fri2": "要烤肉吗？$0#$b#%阿克赖特摆出了两盘热气腾腾的烤肉，香气扑鼻。",
    "SDS.Dialogue.Arkwright.fall_Fri4": "有时在救助站帮忙会遇见奇怪的动物，比如说紫色的乌龟，真的很奇怪。$0#$b#%阿克赖特摸着下巴认真思考着。",
    "SDS.Dialogue.Arkwright.fall_Fri6": "秋天农场会很忙吧？我听说过你们镇子的展览会，加油啊。$0#$b#%阿克赖特站在柜台后面对你竖起了大拇指。",
    "SDS.Dialogue.Arkwright.fall_Fri8": "@总是能很轻松的和别人交流，你有什么交往的秘籍吗？$0#$b#真诚地对待每一个人就可以？我会试试看的，谢谢你。$1",
    "SDS.Dialogue.Arkwright.fall_Fri10": "我听说JOJA的老板就住在最右边大楼的顶层，都说商场如战场，年纪轻轻就能杀出重围成为JOJA的总裁真是不容易。$0",
    "SDS.Dialogue.Arkwright.fall_Sat": "你好。$0#$b#%阿克赖特看着你，但是他的目光好像穿过你看向了远方。",
    "SDS.Dialogue.Arkwright.fall_Sat2": "想买什么？$4",
    "SDS.Dialogue.Arkwright.fall_Sat4": "那个，不嫌弃的话你可以挑喜欢的带走，都是狗狗们捡到的。$0#$b#%你看到柜台上摆着一排擦干净的榛子，上面还有狗狗的牙印呢。",
    "SDS.Dialogue.Arkwright.fall_Sat6": "隔壁的甜品店还有一个小姑娘卖可爱的箱子，小小年纪就能作出独立的设计品真是厉害。$0#$b#%阿克赖特赞赏地点了点头。",
    "SDS.Dialogue.Arkwright.fall_Sat8": "安妮卡女士为狗狗们织了毛茸茸的毯子，这样就不用担心它们夜里着凉了。$0#$b#我和狗狗们受了安妮卡女士很多照顾，真不知道该怎么报答她才好。$2",
    "SDS.Dialogue.Arkwright.fall_Sat10": "我的肌肉很发达？$0#$b#呃，其实我并没有刻意去锻炼肌肉，只是每天进货卖货都是我一个人，下班后还要带狗狗们出去玩，不知不觉间就变成这个身材了。",
    "SDS.Dialogue.Arkwright.fall_Sun": "需要什么自己拿。$4",
    "SDS.Dialogue.Arkwright.fall_Sun2": "买什么？$0#$b#%阿克赖特一边擦着刀一边向你打招呼。",
    "SDS.Dialogue.Arkwright.fall_Sun4": "周末好，今天有炖肉……煎肉和佩莱特饼干，需要什么？$0#$b#%阿克赖特在你鼓励的眼神下努力介绍完了今日菜品，他的头上渗出了一些汗珠。",
    "SDS.Dialogue.Arkwright.fall_Sun6": "我觉得这些日子下来我已经知道该怎么笑了，你觉得怎么样？$1#$b#眼睛弯一点会更好？谢谢你的帮助，你的建议总是很实用。$0",
    "SDS.Dialogue.Arkwright.fall_Sun8": "救助站的女士们帮我在围裙的破洞上绣了狗狗们的图案，作为感谢我买了很多甜品送给了她们，希望她们能喜欢。$1",
    "SDS.Dialogue.Arkwright.fall_Sun10": "农场的活都忙完了吗？$0#$b#一个人经营着那么大的农场可真不容易啊，累了的时候随时来我这坐坐，我会准备很多烤肉给你补充能量的——是给朋友的免费秘制烤肉。$1",
    /*+++++++++++++++++++++++++++++++++++++++++++++++++++++++++++++++++++++++++++++++++++++++++++++++++++++++++++*/
    //[Arkwright Dialogue] Winter
    "SDS.Dialogue.Arkwright.winter_Mon": "买什么？$0",
    "SDS.Dialogue.Arkwright.winter_Mon2": "今天想来点什么？",
    "SDS.Dialogue.Arkwright.winter_Mon4": "呃，嗨……$0#$b#%阿克赖特飞快地收起了柜台上的一本杂志，但是眼尖的你看到了那是一本潮男穿搭教程。",
    "SDS.Dialogue.Arkwright.winter_Mon6": "安妮卡女士总是会过于放大我的优点，这让我很不好意思——$0#$b#你也觉得我很好？这，那个，谢谢你啊。$1",
    "SDS.Dialogue.Arkwright.winter_Mon8": "冬天的时候农场会轻松一些吗？$0#$b#你平时总是很忙，趁着这个机会好好休息吧，闲的时候随时来我这坐坐啊。$1",
    "SDS.Dialogue.Arkwright.winter_Mon10": "前几天带着狗狗们在公园玩的时候听到了几位女士闲聊，穿搭在给别人的第一印象中占比很大。$0#$b#我就想趁着天冷改变一下风格，试了些衣服后发现果然还是帽子和口罩更适合我……。$2",
    "SDS.Dialogue.Arkwright.winter_Tue": "你好。$0#$b#%阿克赖特向你打招呼。",
    "SDS.Dialogue.Arkwright.winter_Tue2": "想要什么就告诉我。",
    "SDS.Dialogue.Arkwright.winter_Tue4": "我会用不同的刀来切不同部位的肉，这样即能减少刀的磨损又能保证肉的口感。",
    "SDS.Dialogue.Arkwright.winter_Tue6": "之前有两个长得一模一样的人卖给了我这把剔骨刀，小巧锋利又价格便宜，真是不错的人啊。$0#$b#%阿克赖特将刀摆成一排向你展示。",
    "SDS.Dialogue.Arkwright.winter_Tue8": "佩莱特收留了一个没有家的小动物，他总说是一只黏人的黑白花狗，直到他给我看了照片——$0#$b#无论怎么看都不是狗啊？",
    "SDS.Dialogue.Arkwright.winter_Tue10": "安妮卡女士很热情，经常来和我聊一会，但你知道我只会烤肉，有时候我真担心会说什么让她伤心的话……$2#$b#你能教教我怎么说话吗？0#$b#%阿克赖特热切地看着你，眼中充满了期待。",
    "SDS.Dialogue.Arkwright.winter_Wed": "来点什么？",
    "SDS.Dialogue.Arkwright.winter_Wed2": "随便看看。$0#$b#%阿克赖特正麻利地将成堆的肉切成小块放进锅里。",
    "SDS.Dialogue.Arkwright.winter_Wed4": "天气很冷，想来点炖肉吗？$1#$b#%阿克赖特揭开了锅盖，香味弥漫在了整个房间。",
    "SDS.Dialogue.Arkwright.winter_Wed6": "我在读信。这位战友的妻子来自遥远的东方，听说她们那会在冬日星盛宴的时候吃一种叫做饺子的食物。$1#$b#你有听说过吗？$0",
    "SDS.Dialogue.Arkwright.winter_Wed8": "店里不忙的时候我会穿的很厚实坐在长椅上吹风。$0#$b#看着路上来来往往的人们总有一种不真实的幸福感，这样的日子真不错啊。$1",
    "SDS.Dialogue.Arkwright.winter_Wed10": "上次佩莱特告诉我，鹈鹕镇的人们每到周五都会聚在镇上的酒吧喝一杯酒暖暖身子。$0#$b#等我说话的能力再提升一些我就试着去凑凑热闹，到时候我一定会主动找你搭话的。$1",
    "SDS.Dialogue.Arkwright.winter_Thu": "……$0#$b#%阿克赖特做出了你好的口型，但没有出声。",
    "SDS.Dialogue.Arkwright.winter_Thu2": "买烤肉吗？",
    "SDS.Dialogue.Arkwright.winter_Thu4": "你别误会，我不是在道上混的，这些肉都是从正规途径进货的！$0#$b#%阿克赖特手忙脚乱地比划着。",
    "SDS.Dialogue.Arkwright.winter_Thu6": "我刚统计完店里的营业额，今天生意很不错呢，待会要去喝两杯吗？$1#$b#请别误会，我是说要去喝热可可吗？$0",
    "SDS.Dialogue.Arkwright.winter_Thu8": "最近天气越来越冷了，晚上睡觉的时候狗狗们会窝在一起。$0#$b#早上醒来的时候却发现它们都挤到我床上来了，看来是时候为狗狗们准备更厚实的被子了。$1",
    "SDS.Dialogue.Arkwright.winter_Thu10": "星露谷的气候很适合居住，不会太冷也不会太热。$0#$b#我接受军事训练的地方在寒冷的北方，每年都会有喝醉酒的人睡在雪地里第二天被发现冻死的事故，太糟糕了。$2",
    "SDS.Dialogue.Arkwright.winter_Fri": "要什么自己拿。",
    "SDS.Dialogue.Arkwright.winter_Fri2": "肉都很新鲜，品质你放心。$0#$b#%阿克赖特小心地将切好的肉装进袋子里递给你。",
    "SDS.Dialogue.Arkwright.winter_Fri4": "冬天真不错啊，很适合来一杯热巧克力，又好喝又能暖手。$1#$b#%阿克赖特端着热巧克力长舒了一口气。",
    "SDS.Dialogue.Arkwright.winter_Fri6": "看这张新的合影$0#$b#我给狗狗们戴上了安妮卡女士织的围巾，小家伙们比平时跑的更欢了，看来它们很喜欢新围巾。$1",
    "SDS.Dialogue.Arkwright.winter_Fri8": "我没有什么爱好，没事干的时候要么在厨房研究做肉的新方法，要么去救助站帮帮忙。$0#$b#能交到你这样可以随意聊天的朋友我很开心。$1",
    "SDS.Dialogue.Arkwright.winter_Fri10": "信使是很伟大的职业，多亏了他们我才能和各自回到家乡的战友们通信。$0#$b#看着战友们的信就像又回到了在军营训练的时候一样，真是一段令人永远怀念的时光啊。$1",
    "SDS.Dialogue.Arkwright.winter_Sat": "你这次要买多少？$0#$b#%阿克赖特打开了电子秤。",
    "SDS.Dialogue.Arkwright.winter_Sat2": "你好。",
    "SDS.Dialogue.Arkwright.winter_Sat4": "呃，那个……周末愉快。$0#$b#%阿克赖特停下手中的活将刀放在桌案上向你挥了挥手。",
    "SDS.Dialogue.Arkwright.winter_Sat6": "有一种叫做冬根的植物在冬天成熟，在军营的时候如果粮草不足我们就会去地里挖一些冬根来填饱可怜的肚子。$1",
    "SDS.Dialogue.Arkwright.winter_Sat8": "安妮卡女士很有亲和力，即使是跟我一起散步，路上碰到的邻居们依然会向她打招呼。$0#$b#感觉被她的光芒照着我也变温柔了。$1",
    "SDS.Dialogue.Arkwright.winter_Sat10": "你也知道我的话不多，有时配上我的表情总是会被人误会。$2#$b#我很感谢你愿意听我慢慢讲还陪我练习说话，交到你这个朋友真是我人生中最幸运的事。$1",
    "SDS.Dialogue.Arkwright.winter_Sun": "买什么？$0#$b#%阿克赖特好像没意识到自己很大声。",
    "SDS.Dialogue.Arkwright.winter_Sun2": "你好……今天新上了熏肉。$0#$b#%阿克赖特拿出一块黑的发亮的熏肉，看起来有点硬。",
    "SDS.Dialogue.Arkwright.winter_Sun4": "我会在傍晚的时候去超市转转，超市每天都会有不同的打折商品，很划算。$1",
    "SDS.Dialogue.Arkwright.winter_Sun6": "虽然冬天很适合热巧克力，但是一定要注意千万不可以给猫猫喂巧克力，这对它们的身体没有好处。$0#$b#%阿克赖特露出了严肃的神情。",
    "SDS.Dialogue.Arkwright.winter_Sun8": "我今天看起来很开心？$1#$b#因为有一位战友和喜欢的姑娘结婚了，能看到朋友找到属于自己的幸福真是太好了。$0#$b#%阿克赖特邀请你坐在他身边一起看随信寄来的照片。",
    "SDS.Dialogue.Arkwright.winter_Sun10": "这么冷的日子让我想起了在军营的时候，冬天总是与烈酒和篝火出现在一起。$0#$b#我不擅长喝酒所以总是蹲在一边烤肉，有人递给我酒我就偷偷浇在肉上，火焰会窜的很高这样烤出来的肉很香。$1"
    /*+++++++++++++++++++++++++++++++++++++++++++++++++++++++++++++++++++++++++++++++++++++++++++++++++++++++++++*/
    /*-----------------------------------------------------------------------------------------------------------*/
}